{
  "sgd_onecycle": {
    "method": "SGD + OneCycleLR",
    "per_epoch": [
      {
        "epoch": 1,
        "accuracy": 46.58,
        "sharpness": 25.101030349731445,
        "time": 56.45465683937073,
        "lr": 0.037222436953018107
      },
      {
        "epoch": 2,
        "accuracy": 61.19,
        "sharpness": 20.86661148071289,
        "time": 105.60528707504272,
        "lr": 0.0822983625987239
      },
      {
        "epoch": 3,
        "accuracy": 68.81,
        "sharpness": 8.959425926208496,
        "time": 152.21312260627747,
        "lr": 0.13797628165862624
      },
      {
        "epoch": 4,
        "accuracy": 72.97,
        "sharpness": 8.632133483886719,
        "time": 199.77549052238464,
        "lr": 0.18294709522862712
      },
      {
        "epoch": 5,
        "accuracy": 77.03,
        "sharpness": 11.275948524475098,
        "time": 247.4944245815277,
        "lr": 0.19999996791787839
      },
      {
        "epoch": 6,
        "accuracy": 80.67,
        "sharpness": 8.852815628051758,
        "time": 294.80241775512695,
        "lr": 0.1987575090010664
      },
      {
        "epoch": 7,
        "accuracy": 69.47,
        "sharpness": 11.372992515563965,
        "time": 341.73152208328247,
        "lr": 0.19508577478714786
      },
      {
        "epoch": 8,
        "accuracy": 73.06,
        "sharpness": 16.66604995727539,
        "time": 389.9762110710144,
        "lr": 0.1890751755582567
      },
      {
        "epoch": 9,
        "accuracy": 76.54,
        "sharpness": 19.898357391357422,
        "time": 436.9769811630249,
        "lr": 0.18087371221544338
      },
      {
        "epoch": 10,
        "accuracy": 81.07,
        "sharpness": 14.41388988494873,
        "time": 484.2619173526764,
        "lr": 0.17068333200530425
      },
      {
        "epoch": 11,
        "accuracy": 82.27,
        "sharpness": 15.470735549926758,
        "time": 532.1059892177582,
        "lr": 0.15875495590854588
      },
      {
        "epoch": 12,
        "accuracy": 75.29,
        "sharpness": 27.491561889648438,
        "time": 579.3916122913361,
        "lr": 0.14538230013268102
      },
      {
        "epoch": 13,
        "accuracy": 78.61,
        "sharpness": 21.808046340942383,
        "time": 625.9601857662201,
        "lr": 0.13089464384421154
      },
      {
        "epoch": 14,
        "accuracy": 82.89,
        "sharpness": 23.40117645263672,
        "time": 673.777325630188,
        "lr": 0.11564872122273412
      },
      {
        "epoch": 15,
        "accuracy": 83.51,
        "sharpness": 29.7681884765625,
        "time": 720.9466655254364,
        "lr": 0.1000199374815058
      },
      {
        "epoch": 16,
        "accuracy": 86.37,
        "sharpness": 20.66676902770996,
        "time": 768.304799079895,
        "lr": 0.08439312514519508
      },
      {
        "epoch": 17,
        "accuracy": 87.55,
        "sharpness": 32.99289321899414,
        "time": 815.7901692390442,
        "lr": 0.06915306819593864
      },
      {
        "epoch": 18,
        "accuracy": 88.22,
        "sharpness": 16.18164825439453,
        "time": 862.7883267402649,
        "lr": 0.054675027414676385
      },
      {
        "epoch": 19,
        "accuracy": 89.2,
        "sharpness": 45.295326232910156,
        "time": 910.5485737323761,
        "lr": 0.04131550021530562
      },
      {
        "epoch": 20,
        "accuracy": 90.04,
        "sharpness": 54.17757034301758,
        "time": 957.2658236026764,
        "lr": 0.029403442495203505
      },
      {
        "epoch": 21,
        "accuracy": 90.71,
        "sharpness": 44.65724182128906,
        "time": 1004.3226816654205,
        "lr": 0.019232168649292065
      },
      {
        "epoch": 22,
        "accuracy": 91.49,
        "sharpness": 84.2528305053711,
        "time": 1052.0924534797668,
        "lr": 0.011052129196180135
      },
      {
        "epoch": 23,
        "accuracy": 92.78,
        "sharpness": 167.66319274902344,
        "time": 1099.6597578525543,
        "lr": 0.005064743855197789
      },
      {
        "epoch": 24,
        "accuracy": 93.21,
        "sharpness": 34.60945510864258,
        "time": 1146.7495017051697,
        "lr": 0.0014174419244327768
      },
      {
        "epoch": 25,
        "accuracy": 93.18,
        "sharpness": 88.77722930908203,
        "time": 1194.7079770565033,
        "lr": 0.00020003208212160143
      }
    ],
    "final_acc": 93.18,
    "best_acc": 93.21,
    "mean_sharpness": 34.13012481689453,
    "peak_sharpness": 167.66319274902344,
    "wall_time": 1194.708178281784
  },
  "kfac_adaptive_damping": {
    "method": "K-FAC + adaptive damping",
    "per_epoch": [
      {
        "epoch": 1,
        "accuracy": 67.39,
        "sharpness": 161.891357421875,
        "time": 84.44403886795044,
        "damping": 0.01
      },
      {
        "epoch": 2,
        "accuracy": 78.79,
        "sharpness": 137.5497283935547,
        "time": 168.7735676765442,
        "damping": 0.008695652173913044
      },
      {
        "epoch": 3,
        "accuracy": 82.87,
        "sharpness": 315.6861267089844,
        "time": 250.79114890098572,
        "damping": 0.007692307692307692
      },
      {
        "epoch": 4,
        "accuracy": 83.78,
        "sharpness": 172.6407470703125,
        "time": 334.4718644618988,
        "damping": 0.006896551724137932
      },
      {
        "epoch": 5,
        "accuracy": 85.3,
        "sharpness": 216.4687042236328,
        "time": 416.6335959434509,
        "damping": 0.0062499999999999995
      },
      {
        "epoch": 6,
        "accuracy": 86.4,
        "sharpness": 334.7356262207031,
        "time": 500.12757086753845,
        "damping": 0.005714285714285714
      },
      {
        "epoch": 7,
        "accuracy": 87.83,
        "sharpness": 263.006591796875,
        "time": 584.3812506198883,
        "damping": 0.005263157894736843
      },
      {
        "epoch": 8,
        "accuracy": 87.43,
        "sharpness": 354.5719909667969,
        "time": 666.305882692337,
        "damping": 0.004878048780487806
      },
      {
        "epoch": 9,
        "accuracy": 88.63,
        "sharpness": 327.3077392578125,
        "time": 750.7747852802277,
        "damping": 0.004545454545454545
      },
      {
        "epoch": 10,
        "accuracy": 88.72,
        "sharpness": 701.7320556640625,
        "time": 832.9828305244446,
        "damping": 0.004255319148936171
      },
      {
        "epoch": 11,
        "accuracy": 89.68,
        "sharpness": 460.26129150390625,
        "time": 917.2978830337524,
        "damping": 0.004
      },
      {
        "epoch": 12,
        "accuracy": 87.43,
        "sharpness": 589.8063354492188,
        "time": 1000.4630479812622,
        "damping": 0.0037735849056603774
      },
      {
        "epoch": 13,
        "accuracy": 89.88,
        "sharpness": 1624.8743896484375,
        "time": 1082.9193303585052,
        "damping": 0.0035714285714285718
      },
      {
        "epoch": 14,
        "accuracy": 89.66,
        "sharpness": 894.744140625,
        "time": 1166.4607388973236,
        "damping": 0.003389830508474576
      },
      {
        "epoch": 15,
        "accuracy": 90.34,
        "sharpness": 889.2216186523438,
        "time": 1248.9815764427185,
        "damping": 0.0032258064516129032
      },
      {
        "epoch": 16,
        "accuracy": 90.12,
        "sharpness": 727.7130737304688,
        "time": 1331.9804117679596,
        "damping": 0.003076923076923077
      },
      {
        "epoch": 17,
        "accuracy": 90.52,
        "sharpness": 1208.9588623046875,
        "time": 1415.17311668396,
        "damping": 0.0029411764705882353
      },
      {
        "epoch": 18,
        "accuracy": 89.89,
        "sharpness": 873.792724609375,
        "time": 1497.1260199546814,
        "damping": 0.0028169014084507044
      },
      {
        "epoch": 19,
        "accuracy": 91.15,
        "sharpness": 1665.2462158203125,
        "time": 1580.1398103237152,
        "damping": 0.002702702702702703
      },
      {
        "epoch": 20,
        "accuracy": 90.55,
        "sharpness": 1920.679931640625,
        "time": 1661.7035627365112,
        "damping": 0.0025974025974025974
      },
      {
        "epoch": 21,
        "accuracy": 90.36,
        "sharpness": 3283.655029296875,
        "time": 1744.7814438343048,
        "damping": 0.0025
      },
      {
        "epoch": 22,
        "accuracy": 90.62,
        "sharpness": 2948.3857421875,
        "time": 1828.0628914833069,
        "damping": 0.0024096385542168672
      },
      {
        "epoch": 23,
        "accuracy": 90.94,
        "sharpness": 5584.0693359375,
        "time": 1909.8017435073853,
        "damping": 0.002325581395348837
      },
      {
        "epoch": 24,
        "accuracy": 91.04,
        "sharpness": 6455.6650390625,
        "time": 1993.293218612671,
        "damping": 0.0022471910112359553
      },
      {
        "epoch": 25,
        "accuracy": 90.89,
        "sharpness": 5362.69873046875,
        "time": 2074.926787376404,
        "damping": 0.002173913043478261
      }
    ],
    "final_acc": 90.89,
    "best_acc": 91.15,
    "mean_sharpness": 1499.0145251464844,
    "peak_sharpness": 6455.6650390625,
    "wall_time": 2074.9270164966583
  }
}